CHANGELOG.txt
MANIFEST.in
README.txt
setup.py
algo_ml.egg-info/PKG-INFO
algo_ml.egg-info/SOURCES.txt
algo_ml.egg-info/dependency_links.txt
algo_ml.egg-info/top_level.txt
algoml/__init__.py