Metadata-Version: 1.1
Name: algo-ml
Version: 0.0.1
Summary: Machine learning Package
Home-page: https://github.com/kukuquack/algo-ml
Author: Omar Zayed
Author-email: kukuquack@gmail.com
License: MIT
Keywords: machine learning ml ai artificial intelligence k-means clustering nearest neighbor regression
Platform: UNKNOWN
Classifier: Development Status :: 5 - Production/Stable
Classifier: Intended Audience :: Education
Classifier: Operating System :: Microsoft :: Windows :: Windows 10
Classifier: License :: OSI Approved :: MIT License
Classifier: Programming Language :: Python :: 3
